morphi/__init__.py
morphi/registry.py
morphi/version.py
morphi/helpers/__init__.py
morphi/helpers/jinja.py
morphi/libs/__init__.py
morphi/libs/packages.py
morphi/messages/__init__.py
morphi/messages/frontend.py
morphi/messages/manager.py
morphi/messages/validation.py
morphi/tests/__init__.py
morphi/tests/test_helpers.py
morphi/tests/test_libs.py
morphi/tests/test_messages.py
morphi/tests/test_registry.py
morphi-0.3.2.dist-info/LICENSE
morphi-0.3.2.dist-info/METADATA
morphi-0.3.2.dist-info/WHEEL
morphi-0.3.2.dist-info/entry_points.txt
morphi-0.3.2.dist-info/top_level.txt
morphi-0.3.2.dist-info/zip-safe
morphi-0.3.2.dist-info/RECORD
