Metadata-Version: 2.1
Name: morphi
Version: 0.3.2
Summary: i18n services for libraries and applications
Home-page: https://github.com/level12/morphi
Author: Level 12 Developers
Author-email: devteam@level12.io
License: BSD
Platform: UNKNOWN
Classifier: Intended Audience :: Developers
Classifier: License :: OSI Approved :: BSD License
Classifier: Operating System :: OS Independent
Classifier: Programming Language :: Python :: 3.7
Classifier: Programming Language :: Python :: 3.8
Classifier: Programming Language :: Python :: 3.9
Classifier: Programming Language :: Python :: 3.10
License-File: LICENSE
Requires-Dist: Babel
Requires-Dist: pytz
Requires-Dist: speaklater
Requires-Dist: tomli
Provides-Extra: develop
Requires-Dist: flake8 ; extra == 'develop'
Requires-Dist: pytest ; extra == 'develop'
Requires-Dist: pytest-cov ; extra == 'develop'
Requires-Dist: tox ; extra == 'develop'
Provides-Extra: tests
Requires-Dist: flake8 ; extra == 'tests'
Requires-Dist: pytest ; extra == 'tests'
Requires-Dist: pytest-cov ; extra == 'tests'
Requires-Dist: tox ; extra == 'tests'
